aedev/project_manager/__init__.py
aedev/project_manager/__main__.py
aedev/project_manager/codeberg.py
aedev/project_manager/templates.py
aedev/project_manager/utils.py
aedev_project_manager-0.3.13.dist-info/licenses/LICENSE.md
aedev_project_manager-0.3.13.dist-info/METADATA
aedev_project_manager-0.3.13.dist-info/WHEEL
aedev_project_manager-0.3.13.dist-info/entry_points.txt
aedev_project_manager-0.3.13.dist-info/top_level.txt
aedev_project_manager-0.3.13.dist-info/zip-safe
aedev_project_manager-0.3.13.dist-info/RECORD
